ADS1219_lib/__init__.py
ADS1219_lib/core.py
ADS1219_lib-0.0.2.dist-info/LICENSE
ADS1219_lib-0.0.2.dist-info/METADATA
ADS1219_lib-0.0.2.dist-info/WHEEL
ADS1219_lib-0.0.2.dist-info/top_level.txt
ADS1219_lib-0.0.2.dist-info/RECORD
