Metadata-Version: 2.1
Name: ADS1219-lib
Version: 0.0.2
Summary: Lib to use ADS1219 with Python on Raspberry
Home-page: https://github.com/mickaelv/ADS1219-Python
Author: Mickaël Veleine
Author-email: contact@mickaelv.fr
License: UNKNOWN
Platform: UNKNOWN
Classifier: Programming Language :: Python
Classifier: Development Status :: 2 - Pre-Alpha
Classifier: License :: OSI Approved :: MIT License
Classifier: Natural Language :: English
Classifier: Operating System :: OS Independent
Classifier: Programming Language :: Python
Classifier: Topic :: System :: Hardware :: Hardware Drivers
Requires-Dist: RPi.GPIO
Requires-Dist: smbus2
